percy/__init__.py
percy/environment.py
percy/screenshot.py
percy/version.py
percy/common/__init__.py
percy/configs/devices.json
percy/errors/__init__.py
percy/lib/__init__.py
percy/lib/app_percy.py
percy/lib/cache.py
percy/lib/cli_wrapper.py
percy/lib/ignore_region.py
percy/lib/percy_automate.py
percy/lib/percy_options.py
percy/lib/region.py
percy/lib/tile.py
percy/metadata/__init__.py
percy/metadata/android_metadata.py
percy/metadata/driver_metadata.py
percy/metadata/ios_metadata.py
percy/metadata/metadata.py
percy/metadata/metadata_resolver.py
percy/providers/__init__.py
percy/providers/app_automate.py
percy/providers/generic_provider.py
percy/providers/provider_resolver.py
percy_appium_app-2.0.4.dist-info/LICENSE
percy_appium_app-2.0.4.dist-info/METADATA
percy_appium_app-2.0.4.dist-info/WHEEL
percy_appium_app-2.0.4.dist-info/top_level.txt
percy_appium_app-2.0.4.dist-info/RECORD
