Metadata-Version: 2.1
Name: percy-appium-app
Version: 2.0.4
Summary: Python client for visual testing with Percy for mobile apps
Home-page: https://github.com/percy/percy-appium-python
Author: Perceptual Inc.
Author-email: team@percy.io
License: MIT
Keywords: appium percy visual testing
Classifier: Development Status :: 2 - Pre-Alpha
Classifier: Intended Audience :: Developers
Classifier: License :: OSI Approved :: MIT License
Classifier: Natural Language :: English
Classifier: Programming Language :: Python :: 3.6
Classifier: Programming Language :: Python :: 3.7
Classifier: Programming Language :: Python :: 3.8
Classifier: Programming Language :: Python :: 3.9
Requires-Python: >=3.6
License-File: LICENSE
Requires-Dist: Appium-Python-Client
Requires-Dist: requests
